eznet_keras/__init__.py
eznet_keras/test.py
eznet_keras/utils.py
eznet_keras/keras2cpp/__init__.py
eznet_keras/keras2cpp/create_unit_tests.py
eznet_keras/keras2cpp/keras2cpp.py
eznet_keras/keras2cpp/python_model.py
eznet_keras/models/__init__.py
eznet_keras/models/ann.py
eznet_keras/models/conv_block.py
eznet_keras/models/conv_network.py
eznet_keras/models/dense_block.py
eznet_keras/models/keras_smart_module.py
eznet_keras/models/recurrent_network.py
eznet_keras/models/var_ae.py
eznet_keras-1.1.3.dist-info/LICENSE.txt
eznet_keras-1.1.3.dist-info/METADATA
eznet_keras-1.1.3.dist-info/WHEEL
eznet_keras-1.1.3.dist-info/top_level.txt
eznet_keras-1.1.3.dist-info/RECORD
