Metadata-Version: 2.1
Name: eznet_keras
Version: 1.1.3
Summary: Easily build Keras models: utils for training/testing, built-in ANN, CNN, RNN models, modular Dense and Convolutional blocks, etc.
Home-page: https://github.com/pniaz20/eznet_keras
Author: Pouya P. Niaz
Author-email: <pniaz20@ku.edu.tr>
License: MIT
Keywords: tensorflow,keras,deep learning,neural network,keras2cpp
Classifier: Development Status :: 3 - Alpha
Classifier: Intended Audience :: End Users/Desktop
Classifier: Intended Audience :: Education
Classifier: Intended Audience :: Science/Research
Classifier: License :: OSI Approved :: MIT License
Classifier: Programming Language :: Python :: 3
Classifier: Operating System :: OS Independent
Classifier: Topic :: Utilities
Classifier: Topic :: Education
Classifier: Topic :: Scientific/Engineering
Classifier: Topic :: Scientific/Engineering :: Artificial Intelligence
Classifier: Topic :: Software Development :: Embedded Systems
Requires-Python: >=3.7, <4
License-File: LICENSE.txt
Requires-Dist: numpy
Requires-Dist: matplotlib
Requires-Dist: tensorflow >=2.4
